
{
  "header": {
    "event": "Allocation failed - JavaScript heap out of memory",
    "location": "OnFatalError",
    "filename": "report.20190314.170602.2032.001.json",
    "dumpEventTime": "2019/03/14 17:06:02",
    "processId": 2032,
    "commandLine": [
      "C:\\Program Files\\nodejs\\node.exe",
      "Q:\\Git React HW\\React\\Task 4 army function\\index.js"
    ],
    "nodejsVersion": "v11.9.0",
    "wordSize": 64,
    "componentVersions": {
      "node": "11.9.0",
      "v8": "7.0.276.38-node.16",
      "uv": "1.25.0",
      "zlib": "1.2.11",
      "brotli": "1.0.7",
      "ares": "1.15.0",
      "modules": "67",
      "nghttp2": "1.34.0",
      "napi": "4",
      "llhttp": "1.0.1",
      "http_parser": "2.8.0",
      "openssl": "1.1.1a",
      "cldr": "34.0",
      "icu": "63.1",
      "tz": "2018e",
      "unicode": "11.0",
      "arch": "x64",
      "platform": "win32",
      "release": "node"
    },
    "osVersion": "Windows 10",
    "machine": "LENOVO-PC4 "
  },
  "javascriptStack": {
    "message": "No stack.",
    "stack": [
      "Unavailable."
    ]
  },
  "nativeStack": [
    " [pc=00007FF635ADCACC] std::basic_ostream<char,std::char_traits<char> >::operator<<+9452",
    " [pc=00007FF635ADBB38] std::basic_ostream<char,std::char_traits<char> >::operator<<+5464",
    " [pc=00007FF635ADB3C2] std::basic_ostream<char,std::char_traits<char> >::operator<<+3554",
    " [pc=00007FF635BD5BFD] uv_loop_fork+82637",
    " [pc=00007FF6360DCAEE] v8::internal::FatalProcessOutOfMemory+798",
    " [pc=00007FF6360DCA27] v8::internal::FatalProcessOutOfMemory+599",
    " [pc=00007FF6363B5844] v8::internal::Heap::RootIsImmortalImmovable+14788",
    " [pc=00007FF6363AB484] v8::internal::Heap::CollectGarbage+7556",
    " [pc=00007FF6363A9B58] v8::internal::Heap::CollectGarbage+1112",
    " [pc=00007FF6363B34C7] v8::internal::Heap::RootIsImmortalImmovable+5703",
    " [pc=00007FF6363B3546] v8::internal::Heap::RootIsImmortalImmovable+5830",
    " [pc=00007FF635F743E1] v8::internal::Factory::NewFillerObject+49",
    " [pc=00007FF6366CF32A] v8::internal::StoreBuffer::StoreBufferOverflow+26826",
    " [pc=0000037616AD0461] "
  ],
  "javascriptHeap": {
    "totalMemory": 1505468416,
    "totalCommittedMemory": 1505468416,
    "usedMemory": 1471449904,
    "availableMemory": 25957144,
    "memoryLimit": 1526909922,
    "heapSpaces": {
      "read_only_space": {
        "memorySize": 524288,
        "committedMemory": 524288,
        "capacity": 515584,
        "used": 33520,
        "available": 482064
      },
      "new_space": {
        "memorySize": 10485760,
        "committedMemory": 10485760,
        "capacity": 5155840,
        "used": 1103360,
        "available": 4052480
      },
      "old_space": {
        "memorySize": 1313017856,
        "committedMemory": 1313017856,
        "capacity": 1291211888,
        "used": 1290997864,
        "available": 214024
      },
      "code_space": {
        "memorySize": 1048576,
        "committedMemory": 1048576,
        "capacity": 558976,
        "used": 558976,
        "available": 0
      },
      "map_space": {
        "memorySize": 536576,
        "committedMemory": 536576,
        "capacity": 233520,
        "used": 233520,
        "available": 0
      },
      "large_object_space": {
        "memorySize": 179855360,
        "committedMemory": 179855360,
        "capacity": 199731240,
        "used": 178522664,
        "available": 21208576
      },
      "new_large_object_space": {
        "memorySize": 0,
        "committedMemory": 0,
        "capacity": 0,
        "used": 0,
        "available": 0
      }
    }
  },
  "libuv": [
  ],
  "environmentVariables": {
    "=::": "::\\",
    "ALLUSERSPROFILE": "C:\\ProgramData",
    "APPDATA": "C:\\Users\\Lenovo\\AppData\\Roaming",
    "COLORTERM": "true",
    "CommonProgramFiles": "C:\\Program Files\\Common Files",
    "CommonProgramFiles(x86)": "C:\\Program Files (x86)\\Common Files",
    "CommonProgramW6432": "C:\\Program Files\\Common Files",
    "COMPUTERNAME": "LENOVO-PC4",
    "ComSpec": "C:\\Windows\\system32\\cmd.exe",
    "DEBUG_COLORS": "true",
    "ELECTRON_NO_ATTACH_CONSOLE": "true",
    "FORCE_COLOR": "true",
    "FPS_BROWSER_APP_PROFILE_STRING": "Internet Explorer",
    "FPS_BROWSER_USER_PROFILE_STRING": "Default",
    "HOMEDRIVE": "C:",
    "HOMEPATH": "\\Users\\Lenovo",
    "LOCALAPPDATA": "C:\\Users\\Lenovo\\AppData\\Local",
    "LOGONSERVER": "\\\\LENOVO-PC4",
    "MOCHA_COLORS": "1",
    "npm_config_color": "always",
    "NUMBER_OF_PROCESSORS": "4",
    "OneDrive": "C:\\Users\\Lenovo\\OneDrive",
    "OS": "Windows_NT",
    "Path": "C:\\Windows\\system32;C:\\Windows;C:\\Windows\\System32\\Wbem;C:\\Windows\\System32\\WindowsPowerShell\\v1.0\\;C:\\Program Files\\Git\\cmd;C:\\Ruby26-x64\\bin;C:\\Program Files\\nodejs\\;C:\\Ruby26-x64\\bin;C:\\Users\\Lenovo\\AppData\\Local\\Microsoft\\WindowsApps;C:\\Program Files\\JetBrains\\PhpStorm 2018.3.3\\bin;;C:\\Users\\Lenovo\\AppData\\Roaming\\npm",
    "PATHEXT": ".COM;.EXE;.BAT;.CMD;.VBS;.VBE;.JS;.JSE;.WSF;.WSH;.MSC;.RB;.RBW",
    "PhpStorm": "C:\\Program Files\\JetBrains\\PhpStorm 2018.3.3\\bin;",
    "PROCESSOR_ARCHITECTURE": "AMD64",
    "PROCESSOR_IDENTIFIER": "Intel64 Family 6 Model 60 Stepping 3, GenuineIntel",
    "PROCESSOR_LEVEL": "6",
    "PROCESSOR_REVISION": "3c03",
    "ProgramData": "C:\\ProgramData",
    "ProgramFiles": "C:\\Program Files",
    "ProgramFiles(x86)": "C:\\Program Files (x86)",
    "ProgramW6432": "C:\\Program Files",
    "PSModulePath": "C:\\Program Files\\WindowsPowerShell\\Modules;C:\\Windows\\system32\\WindowsPowerShell\\v1.0\\Modules",
    "PUBLIC": "C:\\Users\\Public",
    "SESSIONNAME": "Console",
    "SystemDrive": "C:",
    "SystemRoot": "C:\\Windows",
    "TEMP": "C:\\Users\\Lenovo\\AppData\\Local\\Temp",
    "TMP": "C:\\Users\\Lenovo\\AppData\\Local\\Temp",
    "USERDOMAIN": "LENOVO-PC4",
    "USERDOMAIN_ROAMINGPROFILE": "LENOVO-PC4",
    "USERNAME": "Lenovo",
    "USERPROFILE": "C:\\Users\\Lenovo",
    "windir": "C:\\Windows"
  },
  "sharedObjects": [
    "C:\\Program Files\\nodejs\\node.exe",
    "C:\\Windows\\SYSTEM32\\ntdll.dll",
    "C:\\Windows\\System32\\KERNEL32.DLL",
    "C:\\Windows\\System32\\KERNELBASE.dll",
    "C:\\Windows\\SYSTEM32\\apphelp.dll",
    "C:\\Windows\\System32\\PSAPI.DLL",
    "C:\\Windows\\System32\\WS2_32.dll",
    "C:\\Windows\\System32\\RPCRT4.dll",
    "C:\\Windows\\SYSTEM32\\NETAPI32.dll",
    "C:\\Windows\\System32\\msvcrt.dll",
    "C:\\Windows\\System32\\ADVAPI32.dll",
    "C:\\Windows\\System32\\sechost.dll",
    "C:\\Windows\\System32\\USER32.dll",
    "C:\\Windows\\System32\\win32u.dll",
    "C:\\Windows\\System32\\GDI32.dll",
    "C:\\Windows\\SYSTEM32\\dbghelp.dll",
    "C:\\Windows\\System32\\ucrtbase.dll",
    "C:\\Windows\\System32\\gdi32full.dll",
    "C:\\Windows\\System32\\msvcp_win.dll",
    "C:\\Windows\\System32\\CRYPT32.dll",
    "C:\\Windows\\System32\\MSASN1.dll",
    "C:\\Windows\\SYSTEM32\\IPHLPAPI.DLL",
    "C:\\Windows\\SYSTEM32\\USERENV.dll",
    "C:\\Windows\\System32\\profapi.dll",
    "C:\\Windows\\SYSTEM32\\bcrypt.dll",
    "C:\\Windows\\SYSTEM32\\WINMM.dll",
    "C:\\Windows\\SYSTEM32\\winmmbase.dll",
    "C:\\Windows\\SYSTEM32\\NETUTILS.DLL",
    "C:\\Windows\\System32\\cfgmgr32.dll",
    "C:\\Windows\\SYSTEM32\\SRVCLI.DLL",
    "C:\\Windows\\System32\\IMM32.DLL",
    "C:\\Windows\\System32\\combase.dll",
    "C:\\Windows\\System32\\bcryptPrimitives.dll",
    "C:\\Windows\\System32\\powrprof.dll",
    "C:\\Windows\\system32\\mswsock.dll",
    "C:\\Windows\\System32\\kernel.appcore.dll"
  ]
}